Topsis_Chirag_102103554/__init__.py
Topsis_Chirag_102103554/topsis_102103554.py
Topsis_Chirag_102103554-1.0.0.dist-info/LICENSE.txt
Topsis_Chirag_102103554-1.0.0.dist-info/METADATA
Topsis_Chirag_102103554-1.0.0.dist-info/WHEEL
Topsis_Chirag_102103554-1.0.0.dist-info/top_level.txt
Topsis_Chirag_102103554-1.0.0.dist-info/RECORD
