Metadata-Version: 2.1
Name: Topsis-Chirag-102103554
Version: 1.0.0
Summary: A python package for Multiple Criteria Decision Making (MCDM) using Topsis
Home-page: https://github.com/chirag21120/TOPSIS-Chirag-102103554
Download-URL: https://github.com/chirag21120/TOPSIS-Chirag-102103554/archive/v1.0..0tar.gz
Author: Chirag Mohan Gupta
Author-email: mohanchirag2002@gmail.com
License: MIT
Keywords: TOPSIS,102103554,Chirag Mohan Gupta
Classifier: Development Status :: 3 - Alpha
Classifier: Intended Audience :: Developers
Classifier: Topic :: Software Development :: Build Tools
Classifier: License :: OSI Approved :: MIT License
Classifier: Programming Language :: Python :: 3
Classifier: Programming Language :: Python :: 3.4
Classifier: Programming Language :: Python :: 3.5
Classifier: Programming Language :: Python :: 3.6
Classifier: Programming Language :: Python :: 3.7
Classifier: Programming Language :: Python :: 3.8
Classifier: Programming Language :: Python :: 3.9
Classifier: Programming Language :: Python :: 3.10
Classifier: Programming Language :: Python :: 3.11
License-File: LICENSE.txt
Requires-Dist: pandas
Requires-Dist: numpy
